{
  "name": "starktol-vtu-frontend",
  "version": "1.0.0",
  "private": true,
  "scripts": {
    "dev": "next dev",
    "build": "next build",
    "start": "next start",
    "lint": "next lint --fix",
    "clean": "rmdir /s /q .next 2>nul & rmdir /s /q node_modules 2>nul & del package-lock.json 2>nul",
    "reinstall": "npm run clean && npm install",
    "deploy": "npm run clean && npm install && npm run build"
  },
  "dependencies": {
    "next": "14.1.4",
    "react": "18.2.0",
    "react-dom": "18.2.0",
    "@radix-ui/react-slot": "^1.0.2",
    "class-variance-authority": "^0.7.0",
    "clsx": "^2.1.0",
    "tailwind-merge": "^2.2.2",
    "lucide-react": "^0.363.0",
    "axios": "^1.6.8",
    "react-hook-form": "^7.51.0",
    "zod": "^3.22.4",
    "@hookform/resolvers": "^3.3.4",
    "sonner": "^1.4.3",
    "next-themes": "^0.3.0",
    "uuid": "^9.0.1"
  },
  "devDependencies": {
    "@types/node": "^20.11.30",
    "@types/react": "^18.2.73",
    "@types/react-dom": "^18.2.22",
    "@types/uuid": "^9.0.8",
    "autoprefixer": "^10.4.19",
    "eslint": "^8.57.0",
    "eslint-config-next": "14.1.4",
    "postcss": "^8.4.38",
    "tailwindcss": "^3.4.1",
    "typescript": "^5.4.3"
  },
  "engines": {
    "node": ">=18.17.0",
    "npm": ">=9.0.0"
  }
}
